tfhelper/__init__.py
tfhelper/dataset/__init__.py
tfhelper/dataset/dataset.py
tfhelper/gpu/__init__.py
tfhelper/gpu/gpu.py
tfhelper/image/__init__.py
tfhelper/image/image_loader.py
tfhelper/metrics/__init__.py
tfhelper/metrics/geometric_f1_score.py
tfhelper/pruning/__init__.py
tfhelper/pruning/model_saver.py
tfhelper/tensorboard/__init__.py
tfhelper/tensorboard/tensorboard.py
tfhelper/tflite/__init__.py
tfhelper/tflite/converter.py
tfhelper/tflite/tflite.py
tfhelper/transfer_learning/__init__.py
tfhelper/transfer_learning/transfer_learning.py
tfhelper/utils/__init__.py
tfhelper/utils/tfprint.py
tfhelper/visualization/__init__.py
tfhelper/visualization/cam.py
tfhelper-0.0.44.dist-info/METADATA
tfhelper-0.0.44.dist-info/WHEEL
tfhelper-0.0.44.dist-info/top_level.txt
tfhelper-0.0.44.dist-info/RECORD
