Metadata-Version: 2.1
Name: tfhelper
Version: 0.0.44
Summary: This packages contains frequently used methods or classes in use of Tensorflow 2.x
Home-page: https://github.com/JeiKeiLim/tfhelper
Author: Jongkuk Lim
Author-email: lim.jeikei@gmail.com
License: MIT
Platform: UNKNOWN
Classifier: Programming Language :: Python :: 3
Classifier: License :: OSI Approved :: MIT License
Classifier: Operating System :: OS Independent
Requires-Dist: tensorflow (>=2.2.0)
Requires-Dist: matplotlib (>=3.2.1)
Requires-Dist: seaborn (>=0.10.1)
Requires-Dist: tensorflow-model-optimization (>=0.3.0)
Requires-Dist: pandas (>=1.0.3)
Requires-Dist: opencv-python (>=4.2.0)
